Metadata-Version: 1.0
Name: normdistbiondist-probability
Version: 0.1
Summary: Gaussian & Binomial distributions
Home-page: UNKNOWN
Author: Mahmudul Islam
Author-email: mahmudul.du20@gmail.com
License: UNKNOWN
Platform: UNKNOWN
